MLVisualizer/__init__.py
MLVisualizer/main.py
mlvisualizer-1.0.4.dist-info/METADATA
mlvisualizer-1.0.4.dist-info/WHEEL
mlvisualizer-1.0.4.dist-info/top_level.txt
mlvisualizer-1.0.4.dist-info/RECORD
